recipe_cluster/__init__.py
recipe_cluster/__main__.py
recipe_cluster/cli/__init__.py
recipe_cluster/cli/cook.py
recipe_cluster/cli/logging_config.py
recipe_cluster/core/__init__.py
recipe_cluster/core/cluster.py
recipe_cluster/core/degree.py
recipe_cluster/core/go.py
recipe_cluster/core/matrix.py
recipe_cluster/core/utils.py
recipe_cluster-0.0.6.dist-info/licenses/LICENSE
recipe_cluster-0.0.6.dist-info/METADATA
recipe_cluster-0.0.6.dist-info/WHEEL
recipe_cluster-0.0.6.dist-info/entry_points.txt
recipe_cluster-0.0.6.dist-info/top_level.txt
recipe_cluster-0.0.6.dist-info/RECORD
