Metadata-Version: 2.4
Name: recipe-cluster
Version: 0.0.6
Summary: ReCIPE package description
Author: Charlote Versavel
Author-email: focitti <focitt01@gmail.com>, Sam Sledzieski <samsl@mit.edu>
Project-URL: Homepage, https://github.com/focitti/ReCIPE
Project-URL: Issues, https://github.com/focitti/ReCIPE/issues
Classifier: Programming Language :: Python :: 3
Classifier: License :: OSI Approved :: MIT License
Classifier: Operating System :: OS Independent
Requires-Python: >=3.8
License-File: LICENSE
Requires-Dist: numpy>=1.21.0
Requires-Dist: networkx>=3.2.0
Requires-Dist: matplotlib>=3.9.0
Requires-Dist: seaborn>=0.13.2
Requires-Dist: tqdm>=4.66.5
Requires-Dist: scikit-learn>=1.5.0
Requires-Dist: pyvis
Requires-Dist: func-e>=2.0.1
Dynamic: license-file
